chatmemory/__init__.py
chatmemory/chatmemory.py
chatmemory-0.2.8.dist-info/LICENSE
chatmemory-0.2.8.dist-info/METADATA
chatmemory-0.2.8.dist-info/WHEEL
chatmemory-0.2.8.dist-info/top_level.txt
chatmemory-0.2.8.dist-info/RECORD
