Metadata-Version: 2.1
Name: chatmemory
Version: 0.2.8
Summary: The simple yet powerful long-term memory manager between AI and you💕
Home-page: https://github.com/uezo/chatmemory
Author: uezo
Author-email: uezo@uezo.net
Maintainer: uezo
Maintainer-email: uezo@uezo.net
License: Apache v2
Classifier: Programming Language :: Python :: 3
License-File: LICENSE
Requires-Dist: fastapi>=0.115.8
Requires-Dist: openai>=1.64.0
Requires-Dist: uvicorn>=0.34.0
Requires-Dist: psycopg2-binary>=2.9.10
